README.md
setup.py
android_control/__init__.py
android_control/android_helper.py
android_control/android_helper_test.py
android_control.egg-info/PKG-INFO
android_control.egg-info/SOURCES.txt
android_control.egg-info/dependency_links.txt
android_control.egg-info/entry_points.txt
android_control.egg-info/top_level.txt