Metadata-Version: 1.0
Name: android-control
Version: 0.1.2
Summary: The android control tools in https://github.com/tobegit3hub/android_control.
Home-page: https://github.com/tobegit3hub/android_control
Author: tobe
Author-email: tobeg3oogle@gmail.com
License: UNKNOWN
Platform: UNKNOWN
